sudokujf/__init__.py
sudokujf/__main__.py
sudokujf/deduc.py
sudokujf/grille.py
sudokujf-2.3.dist-info/METADATA
sudokujf-2.3.dist-info/WHEEL
sudokujf-2.3.dist-info/top_level.txt
sudokujf-2.3.dist-info/RECORD
