Metadata-Version: 2.1
Name: sudokujf
Version: 2.3
Summary: Un programme en mode texte pour jouer au SUDOKU
Home-page: http://linux.home/PyPI/sudokujf
Author: Jean-François BOUCHAUDY
Author-email: jfbouch@wanadoo.fr
License: MIT
Keywords: sudoku tui deduction
Platform: UNKNOWN
Classifier: License :: OSI Approved :: MIT License
Classifier: Programming Language :: Python :: 3
Classifier: Operating System :: OS Independent
Requires-Python: >=3.6
